{
  "appPageId" : "2aaa669e-9c0e-426e-8582-a633444b7271",
  "componentName" : "siteforce:sldsTwoCol84Layout",
  "id" : "a9b881f6-ae04-4d10-8d0f-5e6c5abb8c3e",
  "label" : "Article Detail",
  "regions" : [ {
    "id" : "29408503-6464-482a-a235-de6a7f243878",
    "regionName" : "header",
    "type" : "region"
  }, {
    "components" : [ {
      "componentAttributes" : {
        "enableVoting" : true,
        "recordId" : "{!recordId}",
        "showTitleInArticleHeader" : true,
        "showTopicPills" : true,
        "urlName" : "{!urlName}"
      },
      "componentName" : "selfService:singleArticleView",
      "id" : "d226e0be-6f48-474a-91a5-90da6bbf9e8e",
      "renderPriority" : "NEUTRAL",
      "renditionMap" : { },
      "type" : "component"
    }, {
      "componentAttributes" : {
        "context" : "RECORD",
        "recordId" : "{!recordId}",
        "width" : "WIDE"
      },
      "componentName" : "forceCommunity:feedPublisher",
      "id" : "21cadda7-32dc-454a-8a59-2eebc7ef1a98",
      "renderPriority" : "NEUTRAL",
      "renditionMap" : { },
      "type" : "component"
    }, {
      "componentAttributes" : {
        "canChangeSorting" : true,
        "defaultFilter" : "",
        "defaultSortOrderHomeFeed" : "Relevance",
        "defaultSortOrderTopicsFeed" : "Relevance",
        "feedDesign" : "DEFAULT",
        "hasFeedSearch" : true,
        "subjectId" : "{!recordId}",
        "type" : "Record"
      },
      "componentName" : "forceCommunity:forceCommunityFeed",
      "id" : "319a2b4c-e8a1-4614-af09-0af3fb8d1f19",
      "renderPriority" : "NEUTRAL",
      "renditionMap" : { },
      "type" : "component"
    } ],
    "id" : "8cd85b8b-6684-44a9-a5d9-b05f95990889",
    "regionName" : "content",
    "type" : "region"
  }, {
    "components" : [ {
      "componentAttributes" : {
        "allowPrepopulatePrechatFields" : true,
        "avatarImgURL" : "",
        "codeSettingsName" : "",
        "defaultMinimizedText" : "Chat with an Expert",
        "displayHelpButton" : true,
        "eswConfigurationJSON" : {
          "baseCoreURL" : "https://guerra4-dev-ed.my.salesforce.com",
          "baseLiveAgentContentURL" : "https://c.la2-c1-cdg.salesforceliveagent.com/content",
          "baseLiveAgentURL" : "https://d.la2-c1-cdg.salesforceliveagent.com/chat",
          "buttonId" : "5737Q000000XkAB",
          "deploymentId" : "5727Q000000Xk1q",
          "enabledFeatures" : [ "LiveAgent" ],
          "entryFeature" : "LiveAgent",
          "eswConfigDevName" : "Chat_Team",
          "eswConfigId" : "04I7Q000000PDjUUAW",
          "eswLiveAgentDevName" : "Chat_Team",
          "gslbBaseURL" : "https://service.force.com",
          "isOfflineCasesEnabled" : "0",
          "orgId" : "00D7Q000000HZZv"
        },
        "externalScripts" : "",
        "externalStyles" : "",
        "fallbackRouting" : "",
        "offlineSupportMinimizedText" : "Contact Us",
        "offlineText" : "Agent Offline",
        "onlineLoadingText" : "Loading",
        "prechatBackgroundImgURL" : "",
        "smallCompanyLogoImgURL" : "",
        "snippetSettingsFile" : "",
        "storageDomain" : "",
        "waitingStateBackgroundImgURL" : ""
      },
      "componentName" : "forceCommunity:embeddedService",
      "id" : "94e7520e-58f1-4131-a5d8-cb7f6ad5cc4b",
      "renderPriority" : "NEUTRAL",
      "renditionMap" : { },
      "type" : "component"
    }, {
      "componentAttributes" : {
        "numberOfItems" : 5,
        "showViewCounts" : true,
        "title" : "Related Articles"
      },
      "componentName" : "selfService:similarArticles42",
      "id" : "ba73ccca-3853-4045-a84a-270f975f45ff",
      "renderPriority" : "NEUTRAL",
      "renditionMap" : { },
      "type" : "component"
    }, {
      "componentAttributes" : {
        "numberOfArticles" : 5,
        "title" : "Trending Articles",
        "topicId" : "{!topicId}"
      },
      "componentName" : "selfService:topicTrendingArticles42",
      "id" : "edec6c19-8490-479f-a309-bbc147a38473",
      "renderPriority" : "NEUTRAL",
      "renditionMap" : { },
      "type" : "component"
    } ],
    "id" : "2efbf525-0909-4584-9804-ef2cac18bd28",
    "regionName" : "sidebar",
    "type" : "region"
  }, {
    "components" : [ {
      "componentAttributes" : {
        "richTextValue" : "<br><br><br>"
      },
      "componentName" : "forceCommunity:htmlBlock",
      "id" : "fa5ee03e-36e7-4e94-8ad8-95635261e6f0",
      "renderPriority" : "NEUTRAL",
      "renditionMap" : { },
      "type" : "component"
    } ],
    "id" : "c48efb53-d4b3-4c12-8031-a1b71a454004",
    "regionName" : "footer",
    "type" : "region"
  }, {
    "components" : [ {
      "componentAttributes" : {
        "customHeadTags" : "",
        "description" : "{!Record.Summary}",
        "title" : "{!Record._Title}"
      },
      "componentName" : "forceCommunity:seoAssistant",
      "id" : "a4f7b7b3-8774-492a-83ba-46786d7d27fc",
      "renditionMap" : { },
      "type" : "component"
    } ],
    "id" : "dadc56fa-c4c5-4f5f-a124-f8d19a19878d",
    "regionName" : "sfdcHiddenRegion",
    "type" : "region"
  } ],
  "themeLayoutType" : "Inner",
  "type" : "view",
  "viewType" : "article"
}